sagaz/__init__.py
sagaz/compensation_graph.py
sagaz/config.py
sagaz/core.py
sagaz/decorators.py
sagaz/exceptions.py
sagaz/hooks.py
sagaz/listeners.py
sagaz/mermaid.py
sagaz/orchestrator.py
sagaz/state_machine.py
sagaz/types.py
sagaz-1.0.3.dist-info/METADATA
sagaz-1.0.3.dist-info/WHEEL
sagaz-1.0.3.dist-info/top_level.txt
sagaz-1.0.3.dist-info/RECORD
