Metadata-Version: 2.4
Name: sagaz
Version: 1.0.3
Summary: Production-ready Saga pattern with DAG support
Requires-Python: >=3.11
Requires-Dist: python-statemachine>=2.1.0
